mersal_msgspec/__init__.py
mersal_msgspec/msgspec_serializer.py
mersal_msgspec/msgspec_serializer_plugin.py
mersal_msgspec/py.typed
mersal_msgspec-0.1.0.dist-info/METADATA
mersal_msgspec-0.1.0.dist-info/WHEEL
mersal_msgspec-0.1.0.dist-info/RECORD
