Metadata-Version: 2.4
Name: mersal-msgspec
Version: 0.1.0
Summary: Add your description here
Author-email: Abdulhaq Emhemmed <abdulhaq.emhemmed@gmail.com>
Requires-Python: >=3.10
Requires-Dist: mersal
Requires-Dist: msgspec
